odoo/addons/energetica_website_sale_order/__init__.py
odoo/addons/energetica_website_sale_order/__manifest__.py
odoo/addons/energetica_website_sale_order/controllers/__init__.py
odoo/addons/energetica_website_sale_order/controllers/main.py
odoo/addons/energetica_website_sale_order/i18n/energetica_website_sale_order.pot
odoo/addons/energetica_website_sale_order/i18n/es.po
odoo/addons/energetica_website_sale_order/models/__init__.py
odoo/addons/energetica_website_sale_order/models/sale_order.py
odoo/addons/energetica_website_sale_order/security/ir.model.access.csv
odoo/addons/energetica_website_sale_order/static/src/js/FormValidation.js
odoo/addons/energetica_website_sale_order/views/lead_template.xml
odoo/addons/energetica_website_sale_order/views/sale_order.xml
odoo/addons/energetica_website_sale_order/views/sale_portal_template.xml
odoo/addons/energetica_website_sale_order/wizards/__init__.py
odoo/addons/energetica_website_sale_order/wizards/send_contract_wizard.py
odoo/addons/energetica_website_sale_order/wizards/send_contract_wizard.xml
odoo_addon_energetica_website_sale_order-16.0.3.1.0.dist-info/METADATA
odoo_addon_energetica_website_sale_order-16.0.3.1.0.dist-info/WHEEL
odoo_addon_energetica_website_sale_order-16.0.3.1.0.dist-info/top_level.txt
odoo_addon_energetica_website_sale_order-16.0.3.1.0.dist-info/RECORD
