Metadata-Version: 2.1
Name: odoo-addon-energetica_website_sale_order
Version: 16.0.3.1.0
Requires-Python: >=3.10
Requires-Dist: odoo-addon-base_rest>=16.0dev,<16.1dev
Requires-Dist: odoo>=16.0a,<16.1dev
Summary: Contract generation from website to sale order.
Home-page: https://coopdevs.org
License: AGPL-3
Author: Coopdevs Treball SCCL
Classifier: Programming Language :: Python
Classifier: Framework :: Odoo
Classifier: Framework :: Odoo :: 16.0
Classifier: License :: OSI Approved :: GNU Affero General Public License v3
